{"node":{"__typename":"GraphImage","id":"2610127934894242431","shortcode":"CQ5CYcZsfp_","dimensions":{"height":1350,"width":1080},"gating_info":null,"fact_check_overall_rating":null,"fact_check_information":null,"media_preview":null,"display_url":"https://scontent-dfw5-1.cdninstagram.com/v/t51.2885-15/210530529_495262664896498_830945346521786829_n.jpg?stp=dst-jpg_e35_p1080x1080&_nc_ht=scontent-dfw5-1.cdninstagram.com&_nc_cat=110&_nc_ohc=TR3eOPiq48YAX9RjxO0&edm=AP_V10EBAAAA&ccb=7-5&oh=00_AfBxjSSjiSz7NrQcdBQoT_R30bafqZ0_onljJuXW-_hn6A&oe=64033AB4&_nc_sid=4f375e","display_resources":[{"src":"https://scontent-dfw5-1.cdninstagram.com/v/t51.2885-15/210530529_495262664896498_830945346521786829_n.jpg?stp=dst-jpg_e35_p640x640_sh0.08&_nc_ht=scontent-dfw5-1.cdninstagram.com&_nc_cat=110&_nc_ohc=TR3eOPiq48YAX9RjxO0&edm=AP_V10EBAAAA&ccb=7-5&oh=00_AfBwVFBJRMSuWQlCdV6LGa-rY1lrrq1DRO-tdtPcBYWr6w&oe=64033AB4&_nc_sid=4f375e","config_width":640,"config_height":800},{"src":"https://scontent-dfw5-1.cdninstagram.com/v/t51.2885-15/210530529_495262664896498_830945346521786829_n.jpg?stp=dst-jpg_e35_p750x750_sh0.08&_nc_ht=scontent-dfw5-1.cdninstagram.com&_nc_cat=110&_nc_ohc=TR3eOPiq48YAX9RjxO0&edm=AP_V10EBAAAA&ccb=7-5&oh=00_AfB5JfEjJ5JFw8zwQ7tLn3UfRJOdsCjIvjNTvjrXU6tq_g&oe=64033AB4&_nc_sid=4f375e","config_width":750,"config_height":937},{"src":"https://scontent-dfw5-1.cdninstagram.com/v/t51.2885-15/210530529_495262664896498_830945346521786829_n.jpg?stp=dst-jpg_e35_p1080x1080&_nc_ht=scontent-dfw5-1.cdninstagram.com&_nc_cat=110&_nc_ohc=TR3eOPiq48YAX9RjxO0&edm=AP_V10EBAAAA&ccb=7-5&oh=00_AfBxjSSjiSz7NrQcdBQoT_R30bafqZ0_onljJuXW-_hn6A&oe=64033AB4&_nc_sid=4f375e","config_width":1080,"config_height":1350}],"accessibility_caption":null,"is_video":false,"tracking_token":"eyJ2ZXJzaW9uIjo1LCJwYXlsb2FkIjp7ImlzX2FuYWx5dGljc190cmFja2VkIjp0cnVlLCJ1dWlkIjoiMDgwNTc3ODJkNTY3NDNlNTg4NGZjOWI5YjgwMmQ4MzgyNjEwMTI3OTM0ODk0MjQyNDMxIn0sInNpZ25hdHVyZSI6IiJ9","edge_media_to_tagged_user":{"edges":[{"node":{"user":{"full_name":"MATCH Malaysia","id":"35143185892","is_verified":false,"profile_pic_url":"https://scontent-dfw5-1.cdninstagram.com/v/t51.2885-19/117891462_1032168353868373_9119211578098900577_n.jpg?stp=dst-jpg_s150x150&_nc_ht=scontent-dfw5-1.cdninstagram.com&_nc_cat=101&_nc_ohc=YmX-D_-sQpsAX_xGkIY&edm=AP_V10EBAAAA&ccb=7-5&oh=00_AfBUSNO0dmzqAzrn7zTd_IXB4Q8Gr3sveXatdhnbRdqSMw&oe=64046C43&_nc_sid=4f375e","username":"match.malaysia"},"x":0.3913043478,"y":0.595410628}}]},"edge_media_to_caption":{"edges":[{"node":{"text":"HOT ITEM\u203c\ufe0f MATCH OCTAGON POD\ud83d\udd25and now @match.malaysia ,RM49.90 SAHAJAA UOLS\u203c\ufe0f CEPAT2\u203c\ufe0f SEBAB LIMITED\u203c\ufe0f\ud83d\udd25 FOLLOW THE STEP\ud83d\udc47\ud83c\udffb\n1.FOLLOW @match.malaysia \ud83d\udd25\n2.TEKAN LINK DI BIO @match.malaysia FOR SEE MORE COLORS \ud83d\ude0d\ud83d\udd25\n\u203c\ufe0f\ud83d\udd25\n#matchoctagon #colourpod #opensystem #refillable #vape #ecigarette #padugiler"}}]},"caption_is_edited":false,"has_ranked_comments":false,"edge_media_to_comment":{"count":16,"page_info":{"has_next_page":true,"end_cursor":""},"edges":[]},"comments_disabled":false,"commenting_disabled_for_viewer":false,"taken_at_timestamp":1625371518,"edge_media_preview_like":{"count":4766,"edges":[]},"edge_media_to_sponsor_user":{"edges":[]},"location":null,"viewer_has_liked":false,"viewer_has_saved":false,"viewer_has_saved_to_collection":false,"viewer_in_photo_of_you":false,"viewer_can_reshare":true,"owner":{"id":"2063860790","is_verified":false,"profile_pic_url":"https://scontent-dfw5-1.cdninstagram.com/v/t51.2885-19/330249750_1595982084182531_1343966337813980250_n.jpg?stp=dst-jpg_s150x150&_nc_ht=scontent-dfw5-1.cdninstagram.com&_nc_cat=111&_nc_ohc=NE2NVaHXP-EAX__vBv6&edm=AP_V10EBAAAA&ccb=7-5&oh=00_AfASxoCUrhAaIK2DIZhmItVBDEUgARq8K1ciNLdUqXtDMQ&oe=640429AB&_nc_sid=4f375e","username":"jessiereenaj","blocked_by_viewer":false,"followed_by_viewer":false,"full_name":"\u2020 \ud835\udc79\ud835\udc90\ud835\udc8e\ud835\udc82\ud835\udc8f \ud835\udc6a\ud835\udc82\ud835\udc95\ud835\udc89\ud835\udc90\ud835\udc8d\ud835\udc8a\ud835\udc84\u2020","has_blocked_viewer":false,"is_private":false,"is_unpublished":false,"requested_by_viewer":false},"is_ad":false,"edge_web_media_to_related_media":{"edges":[]}},"instaloader":{"version":"4.9.5","node_type":"Post"}}