{"node":{"__typename":"GraphSidecar","id":"3011413592280247026","shortcode":"CnKsLT_pary","dimensions":{"height":1080,"width":1080},"gating_info":null,"fact_check_overall_rating":null,"fact_check_information":null,"media_preview":null,"display_url":"https://scontent-dfw5-2.cdninstagram.com/v/t51.2885-15/324062869_908831830110408_1549660425745880053_n.jpg?stp=dst-jpg_e35_s1080x1080&_nc_ht=scontent-dfw5-2.cdninstagram.com&_nc_cat=100&_nc_ohc=dpd4vdpbVjgAX_KFAuv&edm=AP_V10EBAAAA&ccb=7-5&oh=00_AfAmBvzV64ikzlaUnkFiwjUK1M_TAfKdVqIxkkARt06LrQ&oe=645627C9&_nc_sid=4f375e","display_resources":[{"src":"https://scontent-dfw5-2.cdninstagram.com/v/t51.2885-15/324062869_908831830110408_1549660425745880053_n.jpg?stp=dst-jpg_e35_s640x640_sh0.08&_nc_ht=scontent-dfw5-2.cdninstagram.com&_nc_cat=100&_nc_ohc=dpd4vdpbVjgAX_KFAuv&edm=AP_V10EBAAAA&ccb=7-5&oh=00_AfDApGm2uwk5JAgyiXmvux2pax5wU-1Dq5QPtOgznuKQVQ&oe=645627C9&_nc_sid=4f375e","config_width":640,"config_height":640},{"src":"https://scontent-dfw5-2.cdninstagram.com/v/t51.2885-15/324062869_908831830110408_1549660425745880053_n.jpg?stp=dst-jpg_e35_s750x750_sh0.08&_nc_ht=scontent-dfw5-2.cdninstagram.com&_nc_cat=100&_nc_ohc=dpd4vdpbVjgAX_KFAuv&edm=AP_V10EBAAAA&ccb=7-5&oh=00_AfDSFuYgVq7P_z83HQCASqe93dzaQT78keVhe_jjPUUJIA&oe=645627C9&_nc_sid=4f375e","config_width":750,"config_height":750},{"src":"https://scontent-dfw5-2.cdninstagram.com/v/t51.2885-15/324062869_908831830110408_1549660425745880053_n.jpg?stp=dst-jpg_e35_s1080x1080&_nc_ht=scontent-dfw5-2.cdninstagram.com&_nc_cat=100&_nc_ohc=dpd4vdpbVjgAX_KFAuv&edm=AP_V10EBAAAA&ccb=7-5&oh=00_AfAmBvzV64ikzlaUnkFiwjUK1M_TAfKdVqIxkkARt06LrQ&oe=645627C9&_nc_sid=4f375e","config_width":1080,"config_height":1080}],"is_video":false,"tracking_token":"eyJ2ZXJzaW9uIjo1LCJwYXlsb2FkIjp7ImlzX2FuYWx5dGljc190cmFja2VkIjp0cnVlLCJ1dWlkIjoiYzhkYzlhMWVjMDgyNGYzOTljYmY3ZWI0MzFlMGMzMGYzMDExNDEzNTkyMjgwMjQ3MDI2In0sInNpZ25hdHVyZSI6IiJ9","edge_media_to_tagged_user":{"edges":[{"node":{"user":{"full_name":"Leonardo Morales","id":"49059087675","is_verified":false,"profile_pic_url":"https://scontent-dfw5-1.cdninstagram.com/v/t51.2885-19/325448631_882878432859106_7861060878513873187_n.jpg?stp=dst-jpg_s150x150&_nc_ht=scontent-dfw5-1.cdninstagram.com&_nc_cat=110&_nc_ohc=jT94ICrUeFcAX-0zt9u&edm=AP_V10EBAAAA&ccb=7-5&oh=00_AfD6woxbYgrlJpPliJjd6yb_YTtDJdVJL11s7hWg19lmUQ&oe=64577D13&_nc_sid=4f375e","username":"yahel.yf"},"x":0.7546666667,"y":0.735111084}},{"node":{"user":{"full_name":"Shant RiveMon","id":"273418328","is_verified":false,"profile_pic_url":"https://scontent-dfw5-2.cdninstagram.com/v/t51.2885-19/326984973_940762030420958_5151413120021138603_n.jpg?stp=dst-jpg_s150x150&_nc_ht=scontent-dfw5-2.cdninstagram.com&_nc_cat=102&_nc_ohc=R0Fl7eA4KV0AX_uDB7n&edm=AP_V10EBAAAA&ccb=7-5&oh=00_AfD1gCt8MSHu5kaGAr4mmWtPTlaIVI4RIeCkNDD-EncHrg&oe=6456DF8C&_nc_sid=4f375e","username":"shantrivemon"},"x":0.272,"y":0.7724444173}}]},"edge_media_to_caption":{"edges":[{"node":{"text":"Some pics from Day 1 & 2 of visiting Mexico City c: Featuring Grandpa, my aunt, my cousin and dope architecture \ud83e\udd18\ud83c\udffb\n.\u2063\n.\u2063\n.\u2063\n.\u2063\n.\u2063\n.\u2063\n.\u2063\n.\u2063\n.\u2063\n.\u2063\n#cdmx \u269b\ufe0e #cdmxparatodos \u269b\ufe0e #chilango \u269b\ufe0e #dondeir \u269b\ufe0e #frijoles \u269b\ufe0e #lipolaser \u269b\ufe0e #mexicocity \u269b\ufe0e #mexicocityfoodie \u269b\ufe0e #mexicocitywedding \u269b\ufe0e #mexicodf \u269b\ufe0e #mexicotravelchannel \u269b\ufe0e #mexico\ud83c\uddf2\ud83c\uddfd \u269b\ufe0e #museumlover \u269b\ufe0e #paisajecdmx \u269b\ufe0e #polanco \u269b\ufe0e #proyectocdmx \u269b\ufe0e #quantum_hack666 \u269b\ufe0e #sadstories_officialmusic \u269b\ufe0e #streetscenes \u269b\ufe0e #theoriginalhymn \u269b\ufe0e #tulumbeach \u269b\ufe0e #tulummexico \u269b\ufe0e #tulumvibes \u269b\ufe0e #urbanacdmx \u269b\ufe0e #vapeomexico \u269b\ufe0e #vivemexico \u269b\ufe0e #vynil \u269b\ufe0e #waves\ud83c\udf0a \u269b\ufe0e #womeninaviation \u269b\ufe0e #xochimilco \u269b\ufe0e"}}]},"caption_is_edited":false,"has_ranked_comments":false,"edge_media_to_comment":{"count":2,"page_info":{"has_next_page":true,"end_cursor":""},"edges":[]},"comments_disabled":false,"commenting_disabled_for_viewer":false,"taken_at_timestamp":1673208496,"edge_media_preview_like":{"count":73,"edges":[]},"edge_media_to_sponsor_user":{"edges":[]},"location":{"id":"213270076","has_public_page":true,"name":"Mexico City, Mexico","slug":"mexico-city-mexico","address_json":"{\"street_address\": \"\", \"zip_code\": \"\", \"city_name\": \"Mexico City, Mexico\", \"region_name\": \"\", \"country_code\": \"\", \"exact_city_match\": true, \"exact_region_match\": false, \"exact_country_match\": false}"},"viewer_has_liked":false,"viewer_has_saved":false,"viewer_has_saved_to_collection":false,"viewer_in_photo_of_you":false,"viewer_can_reshare":true,"owner":{"id":"5219272286","is_verified":false,"profile_pic_url":"https://scontent-dfw5-1.cdninstagram.com/v/t51.2885-19/274868290_324466409726435_1872571388341329268_n.jpg?stp=dst-jpg_s150x150&_nc_ht=scontent-dfw5-1.cdninstagram.com&_nc_cat=111&_nc_ohc=fnPcxIjO5SsAX8oJHm5&edm=AP_V10EBAAAA&ccb=7-5&oh=00_AfBenwWOWrd9H1EEII_J3OdrofBC4X1pZeOjHEyoBkwBmA&oe=64578C2F&_nc_sid=4f375e","username":"quantum_hack666","blocked_by_viewer":false,"followed_by_viewer":false,"full_name":"\ud835\udc13\ud835\udc21\ud835\udc1e\ud835\udc0e\ud835\udc2b\ud835\udc22\ud835\udc20\ud835\udc22\ud835\udc27\ud835\udc1a\ud835\udc25\ud835\udc07\ud835\udc32\ud835\udc26\ud835\udc27","has_blocked_viewer":false,"is_private":false,"is_unpublished":false,"requested_by_viewer":false},"is_ad":false,"edge_web_media_to_related_media":{"edges":[]},"edge_sidecar_to_children":{"edges":[{"node":{"__typename":"GraphImage","id":"3011413586584405360","shortcode":"CnKsLOsJgVw","dimensions":{"height":1080,"width":1080},"gating_info":null,"fact_check_overall_rating":null,"fact_check_information":null,"media_preview":"ACoq3/NQdD+XNRvtcZ68iq4ZsZ9fxH04qi96g5Bx03Dofy9v88VdiE7k87IjMh/LPJzWbd3OzgHLA8fXpk/ToB+PpSy3xjcSKoZV6E9+P5ioroCbEu3aDgtgcnd7+p7Z+tUtAtcz9xYknknk03I96fMAXO04BPFM8pvaquI3ftW07g+eDxgc1ilieucHqanS2Z+WO38M0xkLy+UnOSAKZKJXmR0WIZ6jr9ea3r9N8LRj0H6Ef4Vy5jYPgc7X257Zzx/KtNtTM5EezBY44Oefbj1rN+RovMpw2pmfYpClQDz9OnHAPsa2F09sD5k/LP696p2waBRIqgkg9eO59eO1OM4PVEqWyrXN5UUDpWJFETctcMcKjsCfTC8fz/Stpen51RmG55FPK5Xg9Pu+lJCMLchBweswYZ4+XnB/Xn0p9lBukjbkZkIyP9kA5BxUjfNbNu52sAM9uvT0qgjsMAEjBBHPf1qxG04bopyMnORnvj1qDD+3/fP/ANeluuq+4/rUAUelZ2vqXex//9k=","display_url":"https://scontent-dfw5-2.cdninstagram.com/v/t51.2885-15/324062869_908831830110408_1549660425745880053_n.jpg?stp=dst-jpg_e35_s1080x1080&_nc_ht=scontent-dfw5-2.cdninstagram.com&_nc_cat=100&_nc_ohc=dpd4vdpbVjgAX_KFAuv&edm=AP_V10EBAAAA&ccb=7-5&oh=00_AfAmBvzV64ikzlaUnkFiwjUK1M_TAfKdVqIxkkARt06LrQ&oe=645627C9&_nc_sid=4f375e","display_resources":[{"src":"https://scontent-dfw5-2.cdninstagram.com/v/t51.2885-15/324062869_908831830110408_1549660425745880053_n.jpg?stp=dst-jpg_e35_s640x640_sh0.08&_nc_ht=scontent-dfw5-2.cdninstagram.com&_nc_cat=100&_nc_ohc=dpd4vdpbVjgAX_KFAuv&edm=AP_V10EBAAAA&ccb=7-5&oh=00_AfDApGm2uwk5JAgyiXmvux2pax5wU-1Dq5QPtOgznuKQVQ&oe=645627C9&_nc_sid=4f375e","config_width":640,"config_height":640},{"src":"https://scontent-dfw5-2.cdninstagram.com/v/t51.2885-15/324062869_908831830110408_1549660425745880053_n.jpg?stp=dst-jpg_e35_s750x750_sh0.08&_nc_ht=scontent-dfw5-2.cdninstagram.com&_nc_cat=100&_nc_ohc=dpd4vdpbVjgAX_KFAuv&edm=AP_V10EBAAAA&ccb=7-5&oh=00_AfDSFuYgVq7P_z83HQCASqe93dzaQT78keVhe_jjPUUJIA&oe=645627C9&_nc_sid=4f375e","config_width":750,"config_height":750},{"src":"https://scontent-dfw5-2.cdninstagram.com/v/t51.2885-15/324062869_908831830110408_1549660425745880053_n.jpg?stp=dst-jpg_e35_s1080x1080&_nc_ht=scontent-dfw5-2.cdninstagram.com&_nc_cat=100&_nc_ohc=dpd4vdpbVjgAX_KFAuv&edm=AP_V10EBAAAA&ccb=7-5&oh=00_AfAmBvzV64ikzlaUnkFiwjUK1M_TAfKdVqIxkkARt06LrQ&oe=645627C9&_nc_sid=4f375e","config_width":1080,"config_height":1080}],"accessibility_caption":null,"is_video":false,"tracking_token":"eyJ2ZXJzaW9uIjo1LCJwYXlsb2FkIjp7ImlzX2FuYWx5dGljc190cmFja2VkIjp0cnVlLCJ1dWlkIjoiYzhkYzlhMWVjMDgyNGYzOTljYmY3ZWI0MzFlMGMzMGYzMDExNDEzNTg2NTg0NDA1MzYwIn0sInNpZ25hdHVyZSI6IiJ9","edge_media_to_tagged_user":{"edges":[{"node":{"user":{"full_name":"Shant RiveMon","id":"273418328","is_verified":false,"profile_pic_url":"https://scontent-dfw5-2.cdninstagram.com/v/t51.2885-19/326984973_940762030420958_5151413120021138603_n.jpg?stp=dst-jpg_s150x150&_nc_ht=scontent-dfw5-2.cdninstagram.com&_nc_cat=102&_nc_ohc=R0Fl7eA4KV0AX_uDB7n&edm=AP_V10EBAAAA&ccb=7-5&oh=00_AfD1gCt8MSHu5kaGAr4mmWtPTlaIVI4RIeCkNDD-EncHrg&oe=6456DF8C&_nc_sid=4f375e","username":"shantrivemon"},"x":0.272,"y":0.7724444173}}]}}},{"node":{"__typename":"GraphImage","id":"3011413586575940765","shortcode":"CnKsLOrpNyd","dimensions":{"height":1079,"width":1080},"gating_info":null,"fact_check_overall_rating":null,"fact_check_information":null,"media_preview":"ACoqw96d1/I/4ilDJ2LD8v8AEUkkLRvsPUdcc1MIoSsjbiNv3AepHv8A/WrW7JsNWRhyrHA9Qfr7ims5brirG5xbbABs3ZLe/anT2yRhHUNtP3/XPX8Dj1o5g5S/aae7w/OMZO4ZOTjHH0zUrTwISpYAjgjA7VRZp4YVl3sMMVAz0x0+vHeswruOTyTzUtc2o07E4BeTIwxPXqM0whwu7BCnjPY1NbGWWTCgMxUg544/+tinybsCPooGSPcHnk+/0q0Q3r6kqXSGNYQD1XPpncM+/NdBfR+bEVGM5B/I1xwJU7hwRyK2YNSmmkWNyME84Ayf8n0qWuqKT7k11bF4VRBxvY9enJrBJIOPSuoeNyPlIGSSSc9zngVkvZTFiQFOSeeOaS9VYPky5BaeW4b+HaR6Yz/PPSqU1uzztGmMHGfZSQcj6YrWNWCBhT3wf50kwsYUenMcPg4L/d77c9T/AJ6VZS0aLy5cEbHJbA5C54Prx+PBrXFOo5mFhCc0zApJuFNQox2jk9BUFH//2Q==","display_url":"https://scontent-dfw5-2.cdninstagram.com/v/t51.2885-15/324230780_100253252962065_6601421623985072761_n.jpg?stp=dst-jpg_e35_s1080x1080&_nc_ht=scontent-dfw5-2.cdninstagram.com&_nc_cat=109&_nc_ohc=dAFUE125heQAX9tib4_&edm=AP_V10EBAAAA&ccb=7-5&oh=00_AfCpHkNIKXlIHQYcGEkKgxKUEOaqZr73up7UKj10c2lIqQ&oe=645645D8&_nc_sid=4f375e","display_resources":[{"src":"https://scontent-dfw5-2.cdninstagram.com/v/t51.2885-15/324230780_100253252962065_6601421623985072761_n.jpg?stp=dst-jpg_e35_s640x640_sh0.08&_nc_ht=scontent-dfw5-2.cdninstagram.com&_nc_cat=109&_nc_ohc=dAFUE125heQAX9tib4_&edm=AP_V10EBAAAA&ccb=7-5&oh=00_AfDA9Kmyx8jm1PUopNxYGNm5o_e6i_qIXHbkAS8YjR-nuw&oe=645645D8&_nc_sid=4f375e","config_width":640,"config_height":639},{"src":"https://scontent-dfw5-2.cdninstagram.com/v/t51.2885-15/324230780_100253252962065_6601421623985072761_n.jpg?stp=dst-jpg_e35_s750x750_sh0.08&_nc_ht=scontent-dfw5-2.cdninstagram.com&_nc_cat=109&_nc_ohc=dAFUE125heQAX9tib4_&edm=AP_V10EBAAAA&ccb=7-5&oh=00_AfDhk7sCiYX8fsktIa1umQEbGikIRwNHi4ljo3pXNOsT2w&oe=645645D8&_nc_sid=4f375e","config_width":750,"config_height":749},{"src":"https://scontent-dfw5-2.cdninstagram.com/v/t51.2885-15/324230780_100253252962065_6601421623985072761_n.jpg?stp=dst-jpg_e35_s1080x1080&_nc_ht=scontent-dfw5-2.cdninstagram.com&_nc_cat=109&_nc_ohc=dAFUE125heQAX9tib4_&edm=AP_V10EBAAAA&ccb=7-5&oh=00_AfCpHkNIKXlIHQYcGEkKgxKUEOaqZr73up7UKj10c2lIqQ&oe=645645D8&_nc_sid=4f375e","config_width":1080,"config_height":1079}],"accessibility_caption":null,"is_video":false,"tracking_token":"eyJ2ZXJzaW9uIjo1LCJwYXlsb2FkIjp7ImlzX2FuYWx5dGljc190cmFja2VkIjp0cnVlLCJ1dWlkIjoiYzhkYzlhMWVjMDgyNGYzOTljYmY3ZWI0MzFlMGMzMGYzMDExNDEzNTg2NTc1OTQwNzY1In0sInNpZ25hdHVyZSI6IiJ9","edge_media_to_tagged_user":{"edges":[]}}},{"node":{"__typename":"GraphImage","id":"3011413586576003525","shortcode":"CnKsLOrpdHF","dimensions":{"height":1080,"width":1080},"gating_info":null,"fact_check_overall_rating":null,"fact_check_information":null,"media_preview":"ACoqyfL5BY8E8n0z3/A9aJ4vLb2YZ/HuPwOahEmSC3IB5HqPSuh+xR3GCTheoAPb9ce/etL21ZFr6IxYWAPPQg1p28kqr2VV6c/KPr3J9ffvUV9p32YB4yWUnGD1HfqOo/KpLYmPB42uMY7D39zmk5dSlG7NDLlQ7gYP8QP/AKEDyB780bW9P1/+vU8K7RnOVPFUGMyEqCCFOBnrgfjU39AcfUw5QjZ2Z4HfvV6HKHC/MFHHPYjPb6/nU9utv5TOoClQQ2Tk9COc+vUYFUrBWVTJj5M4P5df8aG7p+RcVZq/U0WlLRvvORgEDjIA+vfFZq3u3hVG30yc/XP/ANatSOJH+Q8hxg49Ky7yxa2+YHch4z3Hsf8AGlGzVmOWjujTivotu4tj/Z7/AJVntqMhJIAwTVJELdKd5ZrRRivMl8z6BIdnA43DB/POPzwfzrqLOIRwoo/ugn6nk/zrlrn/AFjfWuwg+4n+6P5CiWxCGpbJExZBgkc+n4Dt+FE0QlQo3Rhipz1pKzKOTtoyXZCfu5P1xVvyU9T+VUrckz/i39a3Qi+g/KqaGptKyP/Z","display_url":"https://scontent-dfw5-2.cdninstagram.com/v/t51.2885-15/324062232_1369740256970299_3378215992903192270_n.jpg?stp=dst-jpg_e35_s1080x1080&_nc_ht=scontent-dfw5-2.cdninstagram.com&_nc_cat=107&_nc_ohc=SXwJ4jzWRcMAX9cjYvh&edm=AP_V10EBAAAA&ccb=7-5&oh=00_AfDUyhKRzryhWNDrYL8LaA6hAC9OLYBdWw_KrbmDTramQg&oe=64561315&_nc_sid=4f375e","display_resources":[{"src":"https://scontent-dfw5-2.cdninstagram.com/v/t51.2885-15/324062232_1369740256970299_3378215992903192270_n.jpg?stp=dst-jpg_e35_s640x640_sh0.08&_nc_ht=scontent-dfw5-2.cdninstagram.com&_nc_cat=107&_nc_ohc=SXwJ4jzWRcMAX9cjYvh&edm=AP_V10EBAAAA&ccb=7-5&oh=00_AfBmjGY0soAePWRGo3-n8gU_pTqJ-J1HHFvx4nkLTTGBIw&oe=64561315&_nc_sid=4f375e","config_width":640,"config_height":640},{"src":"https://scontent-dfw5-2.cdninstagram.com/v/t51.2885-15/324062232_1369740256970299_3378215992903192270_n.jpg?stp=dst-jpg_e35_s750x750_sh0.08&_nc_ht=scontent-dfw5-2.cdninstagram.com&_nc_cat=107&_nc_ohc=SXwJ4jzWRcMAX9cjYvh&edm=AP_V10EBAAAA&ccb=7-5&oh=00_AfAbx61Zo_g1UBqi_QsYtJpOW_PtQhUdiSeMSxcvAeWiGA&oe=64561315&_nc_sid=4f375e","config_width":750,"config_height":750},{"src":"https://scontent-dfw5-2.cdninstagram.com/v/t51.2885-15/324062232_1369740256970299_3378215992903192270_n.jpg?stp=dst-jpg_e35_s1080x1080&_nc_ht=scontent-dfw5-2.cdninstagram.com&_nc_cat=107&_nc_ohc=SXwJ4jzWRcMAX9cjYvh&edm=AP_V10EBAAAA&ccb=7-5&oh=00_AfDUyhKRzryhWNDrYL8LaA6hAC9OLYBdWw_KrbmDTramQg&oe=64561315&_nc_sid=4f375e","config_width":1080,"config_height":1080}],"accessibility_caption":null,"is_video":false,"tracking_token":"eyJ2ZXJzaW9uIjo1LCJwYXlsb2FkIjp7ImlzX2FuYWx5dGljc190cmFja2VkIjp0cnVlLCJ1dWlkIjoiYzhkYzlhMWVjMDgyNGYzOTljYmY3ZWI0MzFlMGMzMGYzMDExNDEzNTg2NTc2MDAzNTI1In0sInNpZ25hdHVyZSI6IiJ9","edge_media_to_tagged_user":{"edges":[]}}},{"node":{"__typename":"GraphImage","id":"3011413586659929558","shortcode":"CnKsLOwpm3W","dimensions":{"height":1079,"width":1080},"gating_info":null,"fact_check_overall_rating":null,"fact_check_information":null,"media_preview":"ACoq0iKSpDTcV0HMQXDmONmHUDP6inQyiVA47/5NRXv+pf6f1FM0/wD1I+p/nQVbT5l2lpAaWgQ/FQ3HEbEdlP8AKkM/yNIMMAMrjuMD8c561V+0m4gkJG3apHfnj3qE76ltEBdpLIsxycdfo2KfZn/Rfo3/ALNUKH/QSPY/+hU6z/49G/3v/Zlp31+YNafeagpaQEA8nFNM8QON68e4ouTYwI7oR4K5+X8uevGf/wBfeiS7LgjcQG6jt6evpVGinYsvpdqsJiOT6ce+eef6Uy3uFjV1OfnGBjoDkHpVOlFFg8jZtjLcrlRuZD95jjsegAP8qQ6bN/dH/fX/ANjWI5IPFM3t6n86kdj/2Q==","display_url":"https://scontent-dfw5-1.cdninstagram.com/v/t51.2885-15/324095064_468405855498711_2757988183518725709_n.jpg?stp=dst-jpg_e35_s1080x1080&_nc_ht=scontent-dfw5-1.cdninstagram.com&_nc_cat=103&_nc_ohc=5GPhYO-8KSIAX8I5Rua&edm=AP_V10EBAAAA&ccb=7-5&oh=00_AfC6lukYJJ0MTCHJMKH90Rtu78hRnlhv0RSJrLnRvkltuw&oe=6456082E&_nc_sid=4f375e","display_resources":[{"src":"https://scontent-dfw5-1.cdninstagram.com/v/t51.2885-15/324095064_468405855498711_2757988183518725709_n.jpg?stp=dst-jpg_e35_s640x640_sh0.08&_nc_ht=scontent-dfw5-1.cdninstagram.com&_nc_cat=103&_nc_ohc=5GPhYO-8KSIAX8I5Rua&edm=AP_V10EBAAAA&ccb=7-5&oh=00_AfD-zL1ACY_fHv9mIsyyp256Dzqi3VhKdZ46J_KLYeON1g&oe=6456082E&_nc_sid=4f375e","config_width":640,"config_height":639},{"src":"https://scontent-dfw5-1.cdninstagram.com/v/t51.2885-15/324095064_468405855498711_2757988183518725709_n.jpg?stp=dst-jpg_e35_s750x750_sh0.08&_nc_ht=scontent-dfw5-1.cdninstagram.com&_nc_cat=103&_nc_ohc=5GPhYO-8KSIAX8I5Rua&edm=AP_V10EBAAAA&ccb=7-5&oh=00_AfBRTlRoRK8atoA9IyiAit-m90YzBq2YWvc9bC5GdHI6tA&oe=6456082E&_nc_sid=4f375e","config_width":750,"config_height":749},{"src":"https://scontent-dfw5-1.cdninstagram.com/v/t51.2885-15/324095064_468405855498711_2757988183518725709_n.jpg?stp=dst-jpg_e35_s1080x1080&_nc_ht=scontent-dfw5-1.cdninstagram.com&_nc_cat=103&_nc_ohc=5GPhYO-8KSIAX8I5Rua&edm=AP_V10EBAAAA&ccb=7-5&oh=00_AfC6lukYJJ0MTCHJMKH90Rtu78hRnlhv0RSJrLnRvkltuw&oe=6456082E&_nc_sid=4f375e","config_width":1080,"config_height":1079}],"accessibility_caption":null,"is_video":false,"tracking_token":"eyJ2ZXJzaW9uIjo1LCJwYXlsb2FkIjp7ImlzX2FuYWx5dGljc190cmFja2VkIjp0cnVlLCJ1dWlkIjoiYzhkYzlhMWVjMDgyNGYzOTljYmY3ZWI0MzFlMGMzMGYzMDExNDEzNTg2NjU5OTI5NTU4In0sInNpZ25hdHVyZSI6IiJ9","edge_media_to_tagged_user":{"edges":[]}}},{"node":{"__typename":"GraphImage","id":"3011413586659910089","shortcode":"CnKsLOwpiHJ","dimensions":{"height":1079,"width":1080},"gating_info":null,"fact_check_overall_rating":null,"fact_check_information":null,"media_preview":"ACoq11uAOPT0pGvFUZOf0rBa58o4xnIBP4gGhLrzMgjjDH8gTVJP5CdvmWL698wqFyAMk8/56VcTUwyj5cn696553MjZxz6U4yMoGOxP9K0stjLU17q9aQFMYx15zVETnFRJcM2S3f0AoGKXkVYnlgV3JD4xgYwewH0oSFUUvkkYPVTjp65rQ+1AAD5h0HCjGagurjdFjcfmAyOAQPf0+lZottdjGGWPGTx2B4/xqeGTDbiAdwx0GM9Mjr/TvUG/C4HUHrnt7DqAe/X+dKD5bcdQeCDxxyPr/wDW6VZBpTRGH5QNwbJJwPy4HFUfPPoP1rUkuPkDBsEjODnPtgjj1/Gs0yAHkt+R/wAalFF37cxDOUAXOTznkYA7VWnuhMApBH0P+cinKAV/P+dV3GEYj0/9mFCethtWVyIsuAOwJPTp78nJz6E/zpsYU5DHb07Z/MdePanQfeP+63/oJpyj5R/n+KmQWA5MYTAOCcfnn2P+fxo2k8kjn603/Glyalsm5//Z","display_url":"https://scontent-dfw5-2.cdninstagram.com/v/t51.2885-15/324071094_3008771106094284_5542291654123860949_n.jpg?stp=dst-jpg_e35_s1080x1080&_nc_ht=scontent-dfw5-2.cdninstagram.com&_nc_cat=100&_nc_ohc=yIK5ulcRWfQAX9lzDpP&edm=AP_V10EBAAAA&ccb=7-5&oh=00_AfCZcUYVdxFfOEujh52N9B7qGwevwPsirC9e0IMAA-ZUOg&oe=64577680&_nc_sid=4f375e","display_resources":[{"src":"https://scontent-dfw5-2.cdninstagram.com/v/t51.2885-15/324071094_3008771106094284_5542291654123860949_n.jpg?stp=dst-jpg_e35_s640x640_sh0.08&_nc_ht=scontent-dfw5-2.cdninstagram.com&_nc_cat=100&_nc_ohc=yIK5ulcRWfQAX9lzDpP&edm=AP_V10EBAAAA&ccb=7-5&oh=00_AfB4iMCgksCQmuELHBxbX6FwtYUYHjoWlBmjZRBQj0hSsg&oe=64577680&_nc_sid=4f375e","config_width":640,"config_height":639},{"src":"https://scontent-dfw5-2.cdninstagram.com/v/t51.2885-15/324071094_3008771106094284_5542291654123860949_n.jpg?stp=dst-jpg_e35_s750x750_sh0.08&_nc_ht=scontent-dfw5-2.cdninstagram.com&_nc_cat=100&_nc_ohc=yIK5ulcRWfQAX9lzDpP&edm=AP_V10EBAAAA&ccb=7-5&oh=00_AfC4PX-5rLPRTIxf-FquE7kXzLwevj3bH4dsRQPUEqpcAg&oe=64577680&_nc_sid=4f375e","config_width":750,"config_height":749},{"src":"https://scontent-dfw5-2.cdninstagram.com/v/t51.2885-15/324071094_3008771106094284_5542291654123860949_n.jpg?stp=dst-jpg_e35_s1080x1080&_nc_ht=scontent-dfw5-2.cdninstagram.com&_nc_cat=100&_nc_ohc=yIK5ulcRWfQAX9lzDpP&edm=AP_V10EBAAAA&ccb=7-5&oh=00_AfCZcUYVdxFfOEujh52N9B7qGwevwPsirC9e0IMAA-ZUOg&oe=64577680&_nc_sid=4f375e","config_width":1080,"config_height":1079}],"accessibility_caption":null,"is_video":false,"tracking_token":"eyJ2ZXJzaW9uIjo1LCJwYXlsb2FkIjp7ImlzX2FuYWx5dGljc190cmFja2VkIjp0cnVlLCJ1dWlkIjoiYzhkYzlhMWVjMDgyNGYzOTljYmY3ZWI0MzFlMGMzMGYzMDExNDEzNTg2NjU5OTEwMDg5In0sInNpZ25hdHVyZSI6IiJ9","edge_media_to_tagged_user":{"edges":[]}}},{"node":{"__typename":"GraphImage","id":"3011413586584407189","shortcode":"CnKsLOsJgyV","dimensions":{"height":1079,"width":1080},"gating_info":null,"fact_check_overall_rating":null,"fact_check_information":null,"media_preview":"ACoqzprCWEfNyM8YP9DTPscpGSMD61080Xm4HTBBpptiRgkflWqae5zy518Kv/Xqcr5D9NpPuP8AP60ggk7Ka3gwVGL/AMHf88VUN7Gx4BHHy+pb6+h7dce1F+wXkt0Z7xtj5xg+vY//AF6r4NXvOnOSyllPVSOP8R9fzo8r/Zk/75z+tMtXW/4GpbTNIcNMd45xtGMd8Z6/pUAvZEl2BwwOcliNmOuQccccc5INTM8YGY0QFhhwcjAPoenucdKzbqOJZdiEldo69c8+30rOO9jSSsrmkLZWBVmQqAduG6k84/xz607+zIlO5SWwMhcg8+v/ANb1rFMSp0znPQ4/ljNSLGWyclTx0H+BFXys52/M1pUeEK2G+UdA3Bxz8w45PoM55rJN+55wOfr/AI1Yt7Z5GwzZA55z9B1P+cU9rFsnAGPw/wAaW27LTur7iC9TaC6gleh5FZnmbmLHqT/n9KsXX3B9aqw/eqY9zaXY1b9FaX9185YZIHbgDk9u3XpUD27RIPMGCG/Ag9Dkdam09Q0vIB5HX6itPUFAt2AGACOPxq+ZppdCUrxbG26KkYTqT8x9eemfapdw9P1X/Gs6w6t/u/1qwaykxQVz/9k=","display_url":"https://scontent-dfw5-1.cdninstagram.com/v/t51.2885-15/323955855_491299836453155_4936215742944279449_n.jpg?stp=dst-jpg_e35_s1080x1080&_nc_ht=scontent-dfw5-1.cdninstagram.com&_nc_cat=111&_nc_ohc=KNGSdQQipGUAX9ChqKw&edm=AP_V10EBAAAA&ccb=7-5&oh=00_AfBKbVhDjChHuAsMHZ-uaqVOHMHPDya6zxqz-CBfaI90YQ&oe=645602D7&_nc_sid=4f375e","display_resources":[{"src":"https://scontent-dfw5-1.cdninstagram.com/v/t51.2885-15/323955855_491299836453155_4936215742944279449_n.jpg?stp=dst-jpg_e35_s640x640_sh0.08&_nc_ht=scontent-dfw5-1.cdninstagram.com&_nc_cat=111&_nc_ohc=KNGSdQQipGUAX9ChqKw&edm=AP_V10EBAAAA&ccb=7-5&oh=00_AfAqQIHEdCd6ZG9TR0Wob6fjnLWyFEPvOQI-8BWbjdYymg&oe=645602D7&_nc_sid=4f375e","config_width":640,"config_height":639},{"src":"https://scontent-dfw5-1.cdninstagram.com/v/t51.2885-15/323955855_491299836453155_4936215742944279449_n.jpg?stp=dst-jpg_e35_s750x750_sh0.08&_nc_ht=scontent-dfw5-1.cdninstagram.com&_nc_cat=111&_nc_ohc=KNGSdQQipGUAX9ChqKw&edm=AP_V10EBAAAA&ccb=7-5&oh=00_AfD35yWzqusb3QOiBaa6peXJoUJcJtnIKMOO49Q2GMGqzg&oe=645602D7&_nc_sid=4f375e","config_width":750,"config_height":749},{"src":"https://scontent-dfw5-1.cdninstagram.com/v/t51.2885-15/323955855_491299836453155_4936215742944279449_n.jpg?stp=dst-jpg_e35_s1080x1080&_nc_ht=scontent-dfw5-1.cdninstagram.com&_nc_cat=111&_nc_ohc=KNGSdQQipGUAX9ChqKw&edm=AP_V10EBAAAA&ccb=7-5&oh=00_AfBKbVhDjChHuAsMHZ-uaqVOHMHPDya6zxqz-CBfaI90YQ&oe=645602D7&_nc_sid=4f375e","config_width":1080,"config_height":1079}],"accessibility_caption":null,"is_video":false,"tracking_token":"eyJ2ZXJzaW9uIjo1LCJwYXlsb2FkIjp7ImlzX2FuYWx5dGljc190cmFja2VkIjp0cnVlLCJ1dWlkIjoiYzhkYzlhMWVjMDgyNGYzOTljYmY3ZWI0MzFlMGMzMGYzMDExNDEzNTg2NTg0NDA3MTg5In0sInNpZ25hdHVyZSI6IiJ9","edge_media_to_tagged_user":{"edges":[]}}},{"node":{"__typename":"GraphImage","id":"3011413586592888572","shortcode":"CnKsLOsp3b8","dimensions":{"height":1080,"width":1080},"gating_info":null,"fact_check_overall_rating":null,"fact_check_information":null,"media_preview":"ACoqd8hfeo+Qn1qeEpuw33fesmKN1YjsucD17Up3OME8Aj9OcY961vff0MeTW66a/iTT7Udl25JzjHUflVyyKhCXOTjis122kEE72xuB/oe4PvT7dmTAYcs3TPQYP5elS7WK5X32LMsKNkkDNQ/Zh/s/l/8AWq60ZA4OSBn8ayTcPnt+Q/wq1Z7WM0mn71/vGm+blgMN7dKhicO5Z8nA4A9e3+NMmIbkDbye9JC5HAwPc8fn7VButNhjSMSST1qeUsjIxPVQR249Pf61VqzJMJVVSMFFCgg+hzk0DNieVo4t6HqQAMdAQfyNYu8+la8qeZCABnhDjPtWd9im/uGs6c0o282VNa/cVCcipEZQuCM5681GvQ/T+ooFakIUbQTnn0qYwMnzsMLx/wCPDcBj1x+FQd6s5JjP1X+RosBejvQibtvTCqCc5x3/AA/nTf7Uf0FZlFTyRXQrmbP/2Q==","display_url":"https://scontent-dfw5-1.cdninstagram.com/v/t51.2885-15/324223076_500554615544729_6503696466959111315_n.jpg?stp=dst-jpg_e35_s1080x1080&_nc_ht=scontent-dfw5-1.cdninstagram.com&_nc_cat=105&_nc_ohc=xv-H_6vwOZ0AX_zViLn&edm=AP_V10EBAAAA&ccb=7-5&oh=00_AfDXGvKmzhHMScfAOs-mFD1zUyPKUpdYLQhjVZFHqm64gA&oe=6455FC7B&_nc_sid=4f375e","display_resources":[{"src":"https://scontent-dfw5-1.cdninstagram.com/v/t51.2885-15/324223076_500554615544729_6503696466959111315_n.jpg?stp=dst-jpg_e35_s640x640_sh0.08&_nc_ht=scontent-dfw5-1.cdninstagram.com&_nc_cat=105&_nc_ohc=xv-H_6vwOZ0AX_zViLn&edm=AP_V10EBAAAA&ccb=7-5&oh=00_AfB8JhPKUSTdNL0GGdqZLDUqkoS1Ab0dmBdCM5Icg4HFoA&oe=6455FC7B&_nc_sid=4f375e","config_width":640,"config_height":640},{"src":"https://scontent-dfw5-1.cdninstagram.com/v/t51.2885-15/324223076_500554615544729_6503696466959111315_n.jpg?stp=dst-jpg_e35_s750x750_sh0.08&_nc_ht=scontent-dfw5-1.cdninstagram.com&_nc_cat=105&_nc_ohc=xv-H_6vwOZ0AX_zViLn&edm=AP_V10EBAAAA&ccb=7-5&oh=00_AfCTGHGCnOVwgHI-ParsNPUJSYRNRLWSwtQTaRyvXHIkCg&oe=6455FC7B&_nc_sid=4f375e","config_width":750,"config_height":750},{"src":"https://scontent-dfw5-1.cdninstagram.com/v/t51.2885-15/324223076_500554615544729_6503696466959111315_n.jpg?stp=dst-jpg_e35_s1080x1080&_nc_ht=scontent-dfw5-1.cdninstagram.com&_nc_cat=105&_nc_ohc=xv-H_6vwOZ0AX_zViLn&edm=AP_V10EBAAAA&ccb=7-5&oh=00_AfDXGvKmzhHMScfAOs-mFD1zUyPKUpdYLQhjVZFHqm64gA&oe=6455FC7B&_nc_sid=4f375e","config_width":1080,"config_height":1080}],"accessibility_caption":null,"is_video":false,"tracking_token":"eyJ2ZXJzaW9uIjo1LCJwYXlsb2FkIjp7ImlzX2FuYWx5dGljc190cmFja2VkIjp0cnVlLCJ1dWlkIjoiYzhkYzlhMWVjMDgyNGYzOTljYmY3ZWI0MzFlMGMzMGYzMDExNDEzNTg2NTkyODg4NTcyIn0sInNpZ25hdHVyZSI6IiJ9","edge_media_to_tagged_user":{"edges":[{"node":{"user":{"full_name":"Leonardo Morales","id":"49059087675","is_verified":false,"profile_pic_url":"https://scontent-dfw5-1.cdninstagram.com/v/t51.2885-19/325448631_882878432859106_7861060878513873187_n.jpg?stp=dst-jpg_s150x150&_nc_ht=scontent-dfw5-1.cdninstagram.com&_nc_cat=110&_nc_ohc=jT94ICrUeFcAX-0zt9u&edm=AP_V10EBAAAA&ccb=7-5&oh=00_AfD6woxbYgrlJpPliJjd6yb_YTtDJdVJL11s7hWg19lmUQ&oe=64577D13&_nc_sid=4f375e","username":"yahel.yf"},"x":0.7546666667,"y":0.735111084}}]}}},{"node":{"__typename":"GraphImage","id":"3011413586651586497","shortcode":"CnKsLOwJx_B","dimensions":{"height":1079,"width":1080},"gating_info":null,"fact_check_overall_rating":null,"fact_check_information":null,"media_preview":"ACoqtJbqGyrDJAPX/P4025UIuWZeeMA8/wBafGjMFIjHPU+wPXr3/SqeoRqFBVQkuMkDuOnI/r1qupHTQdFAjKDvTHvjP5YqgXDnap5IOMf/AFsYpxAitydvztgFvTPp9Ome5NUZdgxsyGHX0/PrmnuNF9GZAQWJxnqT/WqGf8/5NWXkIT5uS3U1S+Wsordvud1TRRUbbHQhkxli4wMcD8Rjn261TkKeaGGSGBJyec5x2Pt0rQW0EoLZOD1A9uKheNYHO3IxgZPbOT+v6VtpqeWneyM6YZVihwAASMnn35/DFUYuXHuea6IqsivnBJQ/NwSAAcYH1+lZNpGFkiP95WP4gsP6UkaN2TfYiuW52gcCowoq7Iu5XPVnb06AHpzVZ5PmOBxk44pWtsV7Vz3/AKskdLaZVCP9o478ccVmX8gfPOAW7+3+fyrRsBwfr/U1i3vRv94/zNUupkt0VQ4GR1BHT/PpVizJeSMc/LuH55P4VIVH2INgZ3de/U1a0r/Vn/e/pRe45+6vX9S28YqsbRa0GqOmcL0eh//Z","display_url":"https://scontent-dfw5-1.cdninstagram.com/v/t51.2885-15/323889179_1228284931123287_3223567664304765409_n.jpg?stp=dst-jpg_e35_s1080x1080&_nc_ht=scontent-dfw5-1.cdninstagram.com&_nc_cat=103&_nc_ohc=eK6Ta6KfnzQAX_rZyru&edm=AP_V10EBAAAA&ccb=7-5&oh=00_AfCQtsB8cvdMH7v6cmtAMyfzZuRMz7Xo_Eg3x40rM_DepA&oe=64565681&_nc_sid=4f375e","display_resources":[{"src":"https://scontent-dfw5-1.cdninstagram.com/v/t51.2885-15/323889179_1228284931123287_3223567664304765409_n.jpg?stp=dst-jpg_e35_s640x640_sh0.08&_nc_ht=scontent-dfw5-1.cdninstagram.com&_nc_cat=103&_nc_ohc=eK6Ta6KfnzQAX_rZyru&edm=AP_V10EBAAAA&ccb=7-5&oh=00_AfCHercruieBVmXnjaf7-SGGf-ao6ub3OxzBEVO8Yd7TTg&oe=64565681&_nc_sid=4f375e","config_width":640,"config_height":639},{"src":"https://scontent-dfw5-1.cdninstagram.com/v/t51.2885-15/323889179_1228284931123287_3223567664304765409_n.jpg?stp=dst-jpg_e35_s750x750_sh0.08&_nc_ht=scontent-dfw5-1.cdninstagram.com&_nc_cat=103&_nc_ohc=eK6Ta6KfnzQAX_rZyru&edm=AP_V10EBAAAA&ccb=7-5&oh=00_AfDBOSRUIoTD0AfRSz-BcHCPWEqL4qFSMF2CQqXst-xvxw&oe=64565681&_nc_sid=4f375e","config_width":750,"config_height":749},{"src":"https://scontent-dfw5-1.cdninstagram.com/v/t51.2885-15/323889179_1228284931123287_3223567664304765409_n.jpg?stp=dst-jpg_e35_s1080x1080&_nc_ht=scontent-dfw5-1.cdninstagram.com&_nc_cat=103&_nc_ohc=eK6Ta6KfnzQAX_rZyru&edm=AP_V10EBAAAA&ccb=7-5&oh=00_AfCQtsB8cvdMH7v6cmtAMyfzZuRMz7Xo_Eg3x40rM_DepA&oe=64565681&_nc_sid=4f375e","config_width":1080,"config_height":1079}],"accessibility_caption":null,"is_video":false,"tracking_token":"eyJ2ZXJzaW9uIjo1LCJwYXlsb2FkIjp7ImlzX2FuYWx5dGljc190cmFja2VkIjp0cnVlLCJ1dWlkIjoiYzhkYzlhMWVjMDgyNGYzOTljYmY3ZWI0MzFlMGMzMGYzMDExNDEzNTg2NjUxNTg2NDk3In0sInNpZ25hdHVyZSI6IiJ9","edge_media_to_tagged_user":{"edges":[]}}},{"node":{"__typename":"GraphImage","id":"3011413586584315509","shortcode":"CnKsLOsJKZ1","dimensions":{"height":1079,"width":1080},"gating_info":null,"fact_check_overall_rating":null,"fact_check_information":null,"media_preview":"ACoqJrryRk8k8YBOce4IGBVVdR7FQB/L9aRsSNlyMJk8Z79uQOlLmHbv6AcZxz0z+f8A+ulzW6O4+W630NGKUOm5T68D3PpUkl/GnBbPrtBOPbPrWUqhc7ed+OQT06kcewPPvV9m8rEaoArAcEE9e3H8+aV+u9/wDl/AejpJyuG9/wBealxb9wf1rIuB9jm+TOxxkj26H8uo9KpraMwDY6jP51V7+SJS5e/39v0LNsoYktznn9TVgrHuzuGz/nnt79M4xnr3x7VUAMIG47WwCPTB5H+e1QyXTNwPz71m05SbW39eRqtErmjasFuCif3ePboTitpSQOc/jiuNSVo23qcMO9XzqUxX7w/rV8rJ5jTv7hB8mMuwwOnGeOe/0xQLaQDAfA/3B/8AFVghyzbicn1Naw1PjleaqzW2pDdy5caes25icMVCr6DHeuaaNl5PTJAbsSPQ12HUVzmqMTNjJwOg7D6VMX0NJLqVktmkXcuOuMHj07n1yT9Aaj2lSQMHHpWnCB5DnuIxg/5+p/OswVoZi9KM01utPqkJn//Z","display_url":"https://scontent-dfw5-1.cdninstagram.com/v/t51.2885-15/323929982_829794721458889_913173953979740240_n.jpg?stp=dst-jpg_e35_s1080x1080&_nc_ht=scontent-dfw5-1.cdninstagram.com&_nc_cat=101&_nc_ohc=nxhXEonTooUAX_cM7D5&edm=AP_V10EBAAAA&ccb=7-5&oh=00_AfBJi99xLk6iYFulYSDPwPYmO-WOEZ4xWP_X9KPGn4b_UA&oe=6456AE50&_nc_sid=4f375e","display_resources":[{"src":"https://scontent-dfw5-1.cdninstagram.com/v/t51.2885-15/323929982_829794721458889_913173953979740240_n.jpg?stp=dst-jpg_e35_s640x640_sh0.08&_nc_ht=scontent-dfw5-1.cdninstagram.com&_nc_cat=101&_nc_ohc=nxhXEonTooUAX_cM7D5&edm=AP_V10EBAAAA&ccb=7-5&oh=00_AfCtWKhhuApjDRhzNKPsJdzhnAfdoxPmtPfM_Icr-UiGPw&oe=6456AE50&_nc_sid=4f375e","config_width":640,"config_height":639},{"src":"https://scontent-dfw5-1.cdninstagram.com/v/t51.2885-15/323929982_829794721458889_913173953979740240_n.jpg?stp=dst-jpg_e35_s750x750_sh0.08&_nc_ht=scontent-dfw5-1.cdninstagram.com&_nc_cat=101&_nc_ohc=nxhXEonTooUAX_cM7D5&edm=AP_V10EBAAAA&ccb=7-5&oh=00_AfCcofqMa49hzsvXZ2oQUQMPn-oM2dCJ6Y7tNYeYiM83VQ&oe=6456AE50&_nc_sid=4f375e","config_width":750,"config_height":749},{"src":"https://scontent-dfw5-1.cdninstagram.com/v/t51.2885-15/323929982_829794721458889_913173953979740240_n.jpg?stp=dst-jpg_e35_s1080x1080&_nc_ht=scontent-dfw5-1.cdninstagram.com&_nc_cat=101&_nc_ohc=nxhXEonTooUAX_cM7D5&edm=AP_V10EBAAAA&ccb=7-5&oh=00_AfBJi99xLk6iYFulYSDPwPYmO-WOEZ4xWP_X9KPGn4b_UA&oe=6456AE50&_nc_sid=4f375e","config_width":1080,"config_height":1079}],"accessibility_caption":null,"is_video":false,"tracking_token":"eyJ2ZXJzaW9uIjo1LCJwYXlsb2FkIjp7ImlzX2FuYWx5dGljc190cmFja2VkIjp0cnVlLCJ1dWlkIjoiYzhkYzlhMWVjMDgyNGYzOTljYmY3ZWI0MzFlMGMzMGYzMDExNDEzNTg2NTg0MzE1NTA5In0sInNpZ25hdHVyZSI6IiJ9","edge_media_to_tagged_user":{"edges":[]}}}]}},"instaloader":{"version":"4.9.5","node_type":"Post"}}